pykeygen/__init__.py
pykeygenerator-0.1.1.dist-info/LICENSE
pykeygenerator-0.1.1.dist-info/METADATA
pykeygenerator-0.1.1.dist-info/WHEEL
pykeygenerator-0.1.1.dist-info/top_level.txt
pykeygenerator-0.1.1.dist-info/RECORD
