Metadata-Version: 2.1
Name: pykeygenerator
Version: 0.1.1
Summary: A key generator made in python
Home-page: https://github.com/awesomelewis2007/Pykeygen/
Author: Lewis Evans
Author-email: awesomelewis2007@gmail.com
License: GNU
Platform: UNKNOWN
License-File: LICENSE
